odoo/addons/website_product_configurator_mrp/README.rst
odoo/addons/website_product_configurator_mrp/__init__.py
odoo/addons/website_product_configurator_mrp/__manifest__.py
odoo/addons/website_product_configurator_mrp/controllers/__init__.py
odoo/addons/website_product_configurator_mrp/controllers/main.py
odoo/addons/website_product_configurator_mrp/i18n/de.po
odoo/addons/website_product_configurator_mrp/i18n/website_product_configurator_mrp.pot
odoo/addons/website_product_configurator_mrp/readme/DESCRIPTION.rst
odoo/addons/website_product_configurator_mrp/static/description/icon.png
odoo/addons/website_product_configurator_mrp/static/description/index.html
odoo/addons/website_product_configurator_mrp/static/src/js/website_sale.js
odoo/addons/website_product_configurator_mrp/views/assets.xml
odoo/addons/website_product_configurator_mrp/views/templates.xml
odoo14_addon_website_product_configurator_mrp-14.0.1.0.1.dev10.dist-info/METADATA
odoo14_addon_website_product_configurator_mrp-14.0.1.0.1.dev10.dist-info/WHEEL
odoo14_addon_website_product_configurator_mrp-14.0.1.0.1.dev10.dist-info/top_level.txt
odoo14_addon_website_product_configurator_mrp-14.0.1.0.1.dev10.dist-info/RECORD
